16to1mux/mux16-1.v
// structural hierarchical description using mux4to1
module mux16to1 (in,sel,out);
  input [15:0] in;
  input [3:0] sel;
  output out;
  wire [3:0] t;

  mux4to1 M0 (in[3:0],sel[1:0],t[0]);
  mux4to1 M1 (in[7:4],sel[1:0],t[1]);
  mux4to1 M2 (in[11:8],sel[1:0],t[2]);
  mux4to1 M3 (in[15:12],sel[1:0],t[3]);
  mux4to1 M4 (t,sel[3:2],out);
endmodule

// structural hierarchical description using mux2to1
module mux4to1 (in,sel,out);
  input [3:0] in;
  input [1:0] sel;
  output out;
  wire [1:0] t;

  mux2to1 M0 (in[1:0],sel[0],t[0]);
  mux2to1 M1 (in[3:2],sel[0],t[1]);
  mux2to1 M2 (t,sel[1],out);
endmodule

// structural hierarchical description standard gates
module mux2to1 (in,sel,out);
  input [1:0] in;
  input sel;
  output out;
  wire t,t1,t2;

  not G0 (t,sel);
  and G1 (t1,in[0],t);
  and G2 (t2,in[1],sel);
  or G4 (out,t1,t2);
endmodule

16to1mux/testbench.v
module testbench;
  reg [15:0] I;
  reg [3:0] S;
  wire O;

  mux16to1 DUT(I,S,O);
  initial begin
    $dumpfile("example.vcd");
    $dumpvars(0,testbench);
    $monitor($time," I = %b, S = %d, O = %b", I,S,O);
    #1 I = 16'h3F0A; S = 4'h0;
    repeat (15) #1 S = S + 1;
    #1 $finish;
  end
endmodule

16to1mux/example.vcd
$date
	Sat Aug 29 10:29:42 2020
$end
$version
	Icarus Verilog
$end
$timescale
	1s
$end
$scope module testbench $end
$var wire 1 ! O $end
$var reg 16 " I [15:0] $end
$var reg 4 # S [3:0] $end
$scope module DUT $end
$var wire 16 $ in [15:0] $end
$var wire 4 % sel [3:0] $end
$var wire 4 & t [3:0] $end
$var wire 1 ! out $end
$scope module M0 $end
$var wire 4 ' in [3:0] $end
$var wire 2 ( sel [1:0] $end
$var wire 2 ) t [1:0] $end
$var wire 1 * out $end
$scope module M0 $end
$var wire 2 + in [1:0] $end
$var wire 1 , out $end
$var wire 1 - sel $end
$var wire 1 . t $end
$var wire 1 / t1 $end
$var wire 1 0 t2 $end
$upscope $end
$scope module M1 $end
$var wire 2 1 in [1:0] $end
$var wire 1 2 out $end
$var wire 1 3 sel $end
$var wire 1 4 t $end
$var wire 1 5 t1 $end
$var wire 1 6 t2 $end
$upscope $end
$scope module M2 $end
$var wire 2 7 in [1:0] $end
$var wire 1 * out $end
$var wire 1 8 sel $end
$var wire 1 9 t $end
$var wire 1 : t1 $end
$var wire 1 ; t2 $end
$upscope $end
$upscope $end
$scope module M1 $end
$var wire 4 < in [3:0] $end
$var wire 2 = sel [1:0] $end
$var wire 2 > t [1:0] $end
$var wire 1 ? out $end
$scope module M0 $end
$var wire 2 @ in [1:0] $end
$var wire 1 A out $end
$var wire 1 B sel $end
$var wire 1 C t $end
$var wire 1 D t1 $end
$var wire 1 E t2 $end
$upscope $end
$scope module M1 $end
$var wire 2 F in [1:0] $end
$var wire 1 G out $end
$var wire 1 H sel $end
$var wire 1 I t $end
$var wire 1 J t1 $end
$var wire 1 K t2 $end
$upscope $end
$scope module M2 $end
$var wire 2 L in [1:0] $end
$var wire 1 ? out $end
$var wire 1 M sel $end
$var wire 1 N t $end
$var wire 1 O t1 $end
$var wire 1 P t2 $end
$upscope $end
$upscope $end
$scope module M2 $end
$var wire 4 Q in [3:0] $end
$var wire 2 R sel [1:0] $end
$var wire 2 S t [1:0] $end
$var wire 1 T out $end
$scope module M0 $end
$var wire 2 U in [1:0] $end
$var wire 1 V out $end
$var wire 1 W sel $end
$var wire 1 X t $end
$var wire 1 Y t1 $end
$var wire 1 Z t2 $end
$upscope $end
$scope module M1 $end
$var wire 2 [ in [1:0] $end
$var wire 1 \ out $end
$var wire 1 ] sel $end
$var wire 1 ^ t $end
$var wire 1 _ t1 $end
$var wire 1 ` t2 $end
$upscope $end
$scope module M2 $end
$var wire 2 a in [1:0] $end
$var wire 1 T out $end
$var wire 1 b sel $end
$var wire 1 c t $end
$var wire 1 d t1 $end
$var wire 1 e t2 $end
$upscope $end
$upscope $end
$scope module M3 $end
$var wire 4 f in [3:0] $end
$var wire 2 g sel [1:0] $end
$var wire 2 h t [1:0] $end
$var wire 1 i out $end
$scope module M0 $end
$var wire 2 j in [1:0] $end
$var wire 1 k out $end
$var wire 1 l sel $end
$var wire 1 m t $end
$var wire 1 n t1 $end
$var wire 1 o t2 $end
$upscope $end
$scope module M1 $end
$var wire 2 p in [1:0] $end
$var wire 1 q out $end
$var wire 1 r sel $end
$var wire 1 s t $end
$var wire 1 t t1 $end
$var wire 1 u t2 $end
$upscope $end
$scope module M2 $end
$var wire 2 v in [1:0] $end
$var wire 1 i out $end
$var wire 1 w sel $end
$var wire 1 x t $end
$var wire 1 y t1 $end
$var wire 1 z t2 $end
$upscope $end
$upscope $end
$scope module M4 $end
$var wire 4 { in [3:0] $end
$var wire 2 | sel [1:0] $end
$var wire 2 } t [1:0] $end
$var wire 1 ! out $end
$scope module M0 $end
$var wire 2 ~ in [1:0] $end
$var wire 1 !" out $end
$var wire 1 "" sel $end
$var wire 1 #" t $end
$var wire 1 $" t1 $end
$var wire 1 %" t2 $end
$upscope $end
$scope module M1 $end
$var wire 2 &" in [1:0] $end
$var wire 1 '" out $end
$var wire 1 (" sel $end
$var wire 1 )" t $end
$var wire 1 *" t1 $end
$var wire 1 +" t2 $end
$upscope $end
$scope module M2 $end
$var wire 2 ," in [1:0] $end
$var wire 1 ! out $end
$var wire 1 -" sel $end
$var wire 1 ." t $end
$var wire 1 /" t1 $end
$var wire 1 0" t2 $end
$upscope $end
$upscope $end
$upscope $end
$upscope $end
$enddefinitions $end
#0
$dumpvars
x0"
x/"
x."
x-"
bx ,"
x+"
x*"
x)"
x("
x'"
bx &"
x%"
x$"
x#"
x""
x!"
bx ~
bx }
bx |
bx {
xz
xy
xx
xw
bx v
xu
xt
xs
xr
xq
bx p
xo
xn
xm
xl
xk
bx j
xi
bx h
bx g
bx f
xe
xd
xc
xb
bx a
x`
x_
x^
x]
x\
bx [
xZ
xY
xX
xW
xV
bx U
xT
bx S
bx R
bx Q
xP
xO
xN
xM
bx L
xK
xJ
xI
xH
xG
bx F
xE
xD
xC
xB
xA
bx @
x?
bx >
bx =
bx <
x;
x:
x9
x8
bx 7
x6
x5
x4
x3
x2
bx 1
x0
x/
x.
x-
x,
bx +
x*
bx )
bx (
bx '
bx &
bx %
bx $
bx #
bx "
x!
$end
#1
0!
0/"
0!"
b10 }
b10 ,"
1'"
0$"
1*"
b0 ~
b11 &"
0*
0?
1T
b1100 &
b1100 {
1i
0:
0O
1d
1y
0,
b0 )
b0 7
02
0A
b0 >
b0 L
0G
1V
b11 S
b11 a
1\
1k
b1 h
b1 v
0q
0/
05
0D
0J
1Y
1_
1n
0t
1.
00
14
06
19
0;
1C
0E
1I
0K
1N
0P
1X
0Z
1^
0`
1c
0e
1m
0o
1s
0u
1x
0z
1#"
0%"
1)"
0+"
1."
00"
0-
03
08
0B
0H
0M
0W
0]
0b
0l
0r
0w
0""
0("
0-"
b10 +
b10 1
b0 @
b0 F
b11 U
b11 [
b11 j
b0 p
b0 (
b0 =
b0 R
b0 g
b0 |
b1010 '
b0 <
b1111 Q
b11 f
b0 #
b0 %
b11111100001010 "
b11111100001010 $
#2
1!
1/"
b11 }
b11 ,"
1!"
1$"
b1 ~
b1101 &
b1101 {
1*
1:
1,
b11 )
b11 7
12
0Y
0_
0n
0.
10
04
16
0C
0I
0X
1Z
0^
1`
0m
1o
0s
1-
13
1B
1H
1W
1]
1l
1r
b1 (
b1 =
b1 R
b1 g
b1 #
b1 %
#3
0!
0/"
0!"
b10 }
b10 ,"
1'"
0$"
1*"
b0 ~
0*
1T
b1 &"
b100 &
b100 {
0i
0,
b0 )
b0 7
02
0:
1Y
1V
1_
b11 S
b11 a
1\
0d
1n
b1 h
b1 v
1k
0y
1.
00
14
06
09
0;
1C
1I
0N
1X
0Z
1^
0`
0c
1e
1m
0o
1s
0x
0-
03
18
0B
0H
1M
0W
0]
1b
0l
0r
1w
b10 (
b10 =
b10 R
b10 g
b10 #
b10 %
#4
1!
1/"
b11 }
b11 ,"
1!"
1$"
b1 ~
b101 &
b101 {
1*
1;
1,
b11 )
b11 7
12
0Y
0_
0n
0.
10
04
16
0C
0I
0X
1Z
0^
1`
0m
1o
0s
1-
13
1B
1H
1W
1]
1l
1r
b11 (
b11 =
b11 R
b11 g
b11 #
b11 %
#5
0!
1+"
0/"
b0 ~
b11 &"
1i
0!"
b10 }
b10 ,"
1'"
0,
b0 )
b0 7
02
0:
0*
1Y
1V
1_
b11 S
b11 a
1\
1d
b1100 &
b1100 {
1T
1n
b1 h
b1 v
1k
1y
0$"
0*"
1.
00
14
06
19
0;
1C
1I
1N
1X
0Z
1^
0`
1c
0e
1m
0o
1s
1x
0#"
0)"
0-
03
08
0B
0H
0M
0W
0]
0b
0l
0r
0w
1""
1("
b0 (
b0 =
b0 R
b0 g
b1 |
b100 #
b100 %
#6
b1 ~
b1101 &
b1101 {
1*
1:
1,
b11 )
b11 7
12
0Y
0_
0n
0.
10
04
16
0C
0I
0X
1Z
0^
1`
0m
1o
0s
1-
13
1B
1H
1W
1]
1l
1r
b1 (
b1 =
b1 R
b1 g
b101 #
b101 %
#7
b0 }
b0 ,"
0'"
b0 ~
0+"
0*
1T
b1 &"
b100 &
b100 {
0i
0,
b0 )
b0 7
02
0:
1Y
1V
1_
b11 S
b11 a
1\
0d
1n
b1 h
b1 v
1k
0y
1.
00
14
06
09
0;
1C
1I
0N
1X
0Z
1^
0`
0c
1e
1m
0o
1s
0x
0-
03
18
0B
0H
1M
0W
0]
1b
0l
0r
1w
b10 (
b10 =
b10 R
b10 g
b110 #
b110 %
#8
b1 ~
b101 &
b101 {
1*
1;
1,
b11 )
b11 7
12
0Y
0_
0n
0.
10
04
16
0C
0I
0X
1Z
0^
1`
0m
1o
0s
1-
13
1B
1H
1W
1]
1l
1r
b11 (
b11 =
b11 R
b11 g
b111 #
b111 %
#9
1!
10"
b0 ~
b11 &"
1i
0!"
b10 }
b10 ,"
1'"
0,
b0 )
b0 7
02
0:
0*
1Y
1V
1_
b11 S
b11 a
1\
1d
b1100 &
b1100 {
1T
1n
b1 h
b1 v
1k
1y
0$"
1*"
1.
00
14
06
19
0;
1C
1I
1N
1X
0Z
1^
0`
1c
0e
1m
0o
1s
1x
1#"
1)"
0."
0-
03
08
0B
0H
0M
0W
0]
0b
0l
0r
0w
0""
0("
1-"
b0 (
b0 =
b0 R
b0 g
b10 |
b1000 #
b1000 %
#10
b11 }
b11 ,"
1!"
1$"
b1 ~
b1101 &
b1101 {
1*
1:
1,
b11 )
b11 7
12
0Y
0_
0n
0.
10
04
16
0C
0I
0X
1Z
0^
1`
0m
1o
0s
1-
13
1B
1H
1W
1]
1l
1r
b1 (
b1 =
b1 R
b1 g
b1001 #
b1001 %
#11
1!
10"
0!"
b10 }
b10 ,"
1'"
0$"
1*"
b0 ~
0*
1T
b1 &"
b100 &
b100 {
0i
0,
b0 )
b0 7
02
0:
1Y
1V
1_
b11 S
b11 a
1\
0d
1n
b1 h
b1 v
1k
0y
1.
00
14
06
09
0;
1C
1I
0N
1X
0Z
1^
0`
0c
1e
1m
0o
1s
0x
0-
03
18
0B
0H
1M
0W
0]
1b
0l
0r
1w
b10 (
b10 =
b10 R
b10 g
b1010 #
b1010 %
#12
b11 }
b11 ,"
1!"
1$"
b1 ~
b101 &
b101 {
1*
1;
1,
b11 )
b11 7
12
0Y
0_
0n
0.
10
04
16
0C
0I
0X
1Z
0^
1`
0m
1o
0s
1-
13
1B
1H
1W
1]
1l
1r
b11 (
b11 =
b11 R
b11 g
b1011 #
b1011 %
#13
1!
1+"
10"
b0 ~
b11 &"
1i
0!"
b10 }
b10 ,"
1'"
0,
b0 )
b0 7
02
0:
0*
1Y
1V
1_
b11 S
b11 a
1\
1d
b1100 &
b1100 {
1T
1n
b1 h
b1 v
1k
1y
0$"
0*"
1.
00
14
06
19
0;
1C
1I
1N
1X
0Z
1^
0`
1c
0e
1m
0o
1s
1x
0#"
0)"
0-
03
08
0B
0H
0M
0W
0]
0b
0l
0r
0w
1""
1("
b0 (
b0 =
b0 R
b0 g
b11 |
b1100 #
b1100 %
#14
b1 ~
b1101 &
b1101 {
1*
1:
1,
b11 )
b11 7
12
0Y
0_
0n
0.
10
04
16
0C
0I
0X
1Z
0^
1`
0m
1o
0s
1-
13
1B
1H
1W
1]
1l
1r
b1 (
b1 =
b1 R
b1 g
b1101 #
b1101 %
#15
0!
00"
b0 }
b0 ,"
0'"
b0 ~
0+"
0*
1T
b1 &"
b100 &
b100 {
0i
0,
b0 )
b0 7
02
0:
1Y
1V
1_
b11 S
b11 a
1\
0d
1n
b1 h
b1 v
1k
0y
1.
00
14
06
09
0;
1C
1I
0N
1X
0Z
1^
0`
0c
1e
1m
0o
1s
0x
0-
03
18
0B
0H
1M
0W
0]
1b
0l
0r
1w
b10 (
b10 =
b10 R
b10 g
b1110 #
b1110 %
#16
b1 ~
b101 &
b101 {
1*
1;
1,
b11 )
b11 7
12
0Y
0_
0n
0.
10
04
16
0C
0I
0X
1Z
0^
1`
0m
1o
0s
1-
13
1B
1H
1W
1]
1l
1r
b11 (
b11 =
b11 R
b11 g
b1111 #
b1111 %
