testbenches/displayDirective/displayDirective.v
module fullAdder (S,Cout,A,B,Cin);
  input A,B,Cin;
  output S,Cout;
  wire s1,c1,c2;

  xor G1 (s1,A,B),
      G2 (S,s1,Cin),
      G3 (Cout,c2,c1);
  and G4 (c1,A,B),
      G5 (c2,s1,Cin);
endmodule

module testbench;
	reg A,B,Cin;
	wire S,Cout;
	integer i;
	fullAdder DUT (S,Cout,A,B,Cin);

	initial begin
		$dumpfile ("waveform.vcd");
		$dumpvars (0,testbench);
		for (i=0;i<8;i=i+1) begin
			{A,B,Cin} = i;
			#5 $display ("Time=%2d A=%b B=%b Cin=%b S=%b Cout=%b",$time,A,B,Cin,S,Cout);
		end
		#5 $finish;
	end
endmodule

testbenches/displayDirective/waveform.vcd
$date
	Sat Sep 19 10:43:53 2020
$end
$version
	Icarus Verilog
$end
$timescale
	1s
$end
$scope module testbench $end
$var wire 1 ! S $end
$var wire 1 " Cout $end
$var reg 1 # A $end
$var reg 1 $ B $end
$var reg 1 % Cin $end
$var integer 32 & i [31:0] $end
$scope module DUT $end
$var wire 1 # A $end
$var wire 1 $ B $end
$var wire 1 % Cin $end
$var wire 1 " Cout $end
$var wire 1 ! S $end
$var wire 1 ' c1 $end
$var wire 1 ( c2 $end
$var wire 1 ) s1 $end
$upscope $end
$upscope $end
$enddefinitions $end
#0
$dumpvars
0)
0(
0'
b0 &
0%
0$
0#
0"
0!
$end
#5
1!
1%
b1 &
#10
1)
1!
1$
0%
b10 &
#15
1"
0!
1(
1%
b11 &
#20
0"
1!
0(
1#
0$
0%
b100 &
#25
1"
0!
1(
1%
b101 &
#30
0)
1'
0!
0(
1$
0%
b110 &
#35
1!
1%
b111 &
#40
b1000 &
