FSM/sequenceDetector/sequenceDetector.v
module seqDec (z,x,clk,reset);
	input x,clk,reset;
	output reg z;
	reg [1:0] state;
	parameter S0=0,S1=1,S2=2,S3=3;

	always @(posedge clk or posedge reset) begin
		if (reset) state = S0;
		else case (state)
			S0 : begin state = x ? S0 : S1; z = 0; end
			S1 : begin state = x ? S2 : S1; z = 0; end
			S2 : begin state = x ? S3 : S1; z = 0; end
			S3 : begin
				state = x ? S0 : S1;
				if (~x) z = 1;
				else z = 0;
			end
			default : begin state = S0; z = 0; end
		endcase
	end
endmodule

module testbench;
	integer i;
	wire z;
	reg x,clk,reset;
	reg [31:0] constant;
	seqDec DUT (z,x,clk,reset);

	initial begin
		clk = 0;
		reset = 0;
		constant = 32'b01101100111000101101001110101010;
		#1 reset = 1;
		#1 reset = 0;
		for (i=0;i<32;i=i+1)	begin
			x = constant[i]; #10
			$display ($time," : const=%b : i=%2d : x=%b : z = %b",constant,i,x,z);
		end
	end

	always #5 clk = ~clk;

	initial begin
		$dumpfile ("waveform.vcd");
		$dumpvars (0,testbench);
	end

	initial #1000 $finish;
endmodule

FSM/sequenceDetector/waveform.vcd
$date
	Wed Sep 23 19:54:04 2020
$end
$version
	Icarus Verilog
$end
$timescale
	1s
$end
$scope module testbench $end
$var wire 1 ! z $end
$var reg 1 " clk $end
$var reg 32 # constant [31:0] $end
$var reg 1 $ reset $end
$var reg 1 % x $end
$var integer 32 & i [31:0] $end
$scope module DUT $end
$var wire 1 " clk $end
$var wire 1 $ reset $end
$var wire 1 % x $end
$var reg 2 ' state [1:0] $end
$var reg 1 ! z $end
$upscope $end
$upscope $end
$enddefinitions $end
#0
$dumpvars
bx '
bx &
x%
0$
b1101100111000101101001110101010 #
0"
x!
$end
#1
b0 '
1$
#2
0%
b0 &
0$
#5
0!
b1 '
1"
#10
0"
#12
1%
b1 &
#15
b10 '
1"
#20
0"
#22
0%
b10 &
#25
b1 '
1"
#30
0"
#32
1%
b11 &
#35
b10 '
1"
#40
0"
#42
0%
b100 &
#45
b1 '
1"
#50
0"
#52
1%
b101 &
#55
b10 '
1"
#60
0"
#62
0%
b110 &
#65
b1 '
1"
#70
0"
#72
1%
b111 &
#75
b10 '
1"
#80
0"
#82
b1000 &
#85
b11 '
1"
#90
0"
#92
b1001 &
#95
b0 '
1"
#100
0"
#102
0%
b1010 &
#105
b1 '
1"
#110
0"
#112
b1011 &
#115
1"
#120
0"
#122
1%
b1100 &
#125
b10 '
1"
#130
0"
#132
0%
b1101 &
#135
b1 '
1"
#140
0"
#142
1%
b1110 &
#145
b10 '
1"
#150
0"
#152
b1111 &
#155
b11 '
1"
#160
0"
#162
0%
b10000 &
#165
1!
b1 '
1"
#170
0"
#172
1%
b10001 &
#175
0!
b10 '
1"
#180
0"
#182
0%
b10010 &
#185
b1 '
1"
#190
0"
#192
b10011 &
#195
1"
#200
0"
#202
b10100 &
#205
1"
#210
0"
#212
1%
b10101 &
#215
b10 '
1"
#220
0"
#222
b10110 &
#225
b11 '
1"
#230
0"
#232
b10111 &
#235
b0 '
1"
#240
0"
#242
0%
b11000 &
#245
b1 '
1"
#250
0"
#252
b11001 &
#255
1"
#260
0"
#262
1%
b11010 &
#265
b10 '
1"
#270
0"
#272
b11011 &
#275
b11 '
1"
#280
0"
#282
0%
b11100 &
#285
1!
b1 '
1"
#290
0"
#292
1%
b11101 &
#295
0!
b10 '
1"
#300
0"
#302
b11110 &
#305
b11 '
1"
#310
0"
#312
0%
b11111 &
#315
1!
b1 '
1"
#320
0"
#322
b100000 &
#325
0!
1"
