counter/counter.v
module simpleCounter (clk,rst,count);
  input clk,rst;
  output [7:0] count;
  reg [7:0] count;

  always @ (posedge clk or posedge rst) begin
    if (rst)
      count = 8'b0;
    else
      count = count + 1;
  end
endmodule

module clock (clk);
  output reg clk = 0;
  always
    #10 clk = ~clk;
endmodule

counter/testbench.v
module testbench;
  wire clk;
  reg rst;
  wire [7:0] count;
  simpleCounter DUT(clk,rst,count);
  clock genclk(clk);

  initial begin
    $dumpfile ("example.vcd");
    $dumpvars (0,testbench);
    $monitor ($time," count = %d, clock = %b, Reset = %b",count,clk,rst);
    rst = 0;
    #1 rst = 1;
    #1 rst = 0;
    #1000 $finish;
  end
endmodule

counter/example.vcd
$date
	Fri Sep 11 07:48:30 2020
$end
$version
	Icarus Verilog
$end
$timescale
	1s
$end
$scope module testbench $end
$var wire 8 ! count [7:0] $end
$var wire 1 " clk $end
$var reg 1 # rst $end
$scope module DUT $end
$var wire 1 # rst $end
$var wire 1 " clk $end
$var reg 8 $ count [7:0] $end
$upscope $end
$scope module genclk $end
$var reg 1 " clk $end
$upscope $end
$upscope $end
$enddefinitions $end
#0
$dumpvars
bx $
0#
0"
bx !
$end
#1
b0 !
b0 $
1#
#2
0#
#10
b1 !
b1 $
1"
#20
0"
#30
b10 !
b10 $
1"
#40
0"
#50
b11 !
b11 $
1"
#60
0"
#70
b100 !
b100 $
1"
#80
0"
#90
b101 !
b101 $
1"
#100
0"
#110
b110 !
b110 $
1"
#120
0"
#130
b111 !
b111 $
1"
#140
0"
#150
b1000 !
b1000 $
1"
#160
0"
#170
b1001 !
b1001 $
1"
#180
0"
#190
b1010 !
b1010 $
1"
#200
0"
#210
b1011 !
b1011 $
1"
#220
0"
#230
b1100 !
b1100 $
1"
#240
0"
#250
b1101 !
b1101 $
1"
#260
0"
#270
b1110 !
b1110 $
1"
#280
0"
#290
b1111 !
b1111 $
1"
#300
0"
#310
b10000 !
b10000 $
1"
#320
0"
#330
b10001 !
b10001 $
1"
#340
0"
#350
b10010 !
b10010 $
1"
#360
0"
#370
b10011 !
b10011 $
1"
#380
0"
#390
b10100 !
b10100 $
1"
#400
0"
#410
b10101 !
b10101 $
1"
#420
0"
#430
b10110 !
b10110 $
1"
#440
0"
#450
b10111 !
b10111 $
1"
#460
0"
#470
b11000 !
b11000 $
1"
#480
0"
#490
b11001 !
b11001 $
1"
#500
0"
#510
b11010 !
b11010 $
1"
#520
0"
#530
b11011 !
b11011 $
1"
#540
0"
#550
b11100 !
b11100 $
1"
#560
0"
#570
b11101 !
b11101 $
1"
#580
0"
#590
b11110 !
b11110 $
1"
#600
0"
#610
b11111 !
b11111 $
1"
#620
0"
#630
b100000 !
b100000 $
1"
#640
0"
#650
b100001 !
b100001 $
1"
#660
0"
#670
b100010 !
b100010 $
1"
#680
0"
#690
b100011 !
b100011 $
1"
#700
0"
#710
b100100 !
b100100 $
1"
#720
0"
#730
b100101 !
b100101 $
1"
#740
0"
#750
b100110 !
b100110 $
1"
#760
0"
#770
b100111 !
b100111 $
1"
#780
0"
#790
b101000 !
b101000 $
1"
#800
0"
#810
b101001 !
b101001 $
1"
#820
0"
#830
b101010 !
b101010 $
1"
#840
0"
#850
b101011 !
b101011 $
1"
#860
0"
#870
b101100 !
b101100 $
1"
#880
0"
#890
b101101 !
b101101 $
1"
#900
0"
#910
b101110 !
b101110 $
1"
#920
0"
#930
b101111 !
b101111 $
1"
#940
0"
#950
b110000 !
b110000 $
1"
#960
0"
#970
b110001 !
b110001 $
1"
#980
0"
#990
b110010 !
b110010 $
1"
