shiftReg4Bit/shiftReg.v
module shiftReg4bit (clk,clear,A,out);
  input clk,clear,A;
  output reg out;
  reg B,C,D;

  always @(posedge clk or negedge clear) begin
    if(!clear) begin
      B=0;C=0;D=0;out=0;
    end
    else begin
      //out=D;D=C;C=B;B=A; order matters
      B<=A;C<=B;D<=C;out<=D; //orfer does not matter
    end
  end
endmodule

module testbench;
  reg clk,clear,A;
  wire out;
  shiftReg4bit DUT(clk,clear,A,out);

  initial begin
    $dumpfile("example.vcd");
    $dumpvars(0,testbench);
    $monitor($time," A = %b, out = %b, clk =%b, clear = %b",A,out,clk,clear);
    clear=1;clk=0;A=0;
    #1 clear=0;
    #1 clear=1;
    forever
      #5 clk = ~clk;
  end
  initial forever #10 A = ~A;
  initial #1000 $finish;
endmodule

shiftReg4Bit/example.vcd
$date
	Mon Sep 14 16:55:18 2020
$end
$version
	Icarus Verilog
$end
$timescale
	1s
$end
$scope module testbench $end
$var wire 1 ! out $end
$var reg 1 " A $end
$var reg 1 # clear $end
$var reg 1 $ clk $end
$scope module DUT $end
$var wire 1 " A $end
$var wire 1 # clear $end
$var wire 1 $ clk $end
$var reg 1 % B $end
$var reg 1 & C $end
$var reg 1 ' D $end
$var reg 1 ! out $end
$upscope $end
$upscope $end
$enddefinitions $end
#0
$dumpvars
x'
x&
x%
0$
1#
0"
x!
$end
#1
0!
0'
0&
0%
0#
#2
1#
#7
1$
#10
1"
#12
0$
#17
1%
1$
#20
0"
#22
0$
#27
1&
0%
1$
#30
1"
#32
0$
#37
1'
0&
1%
1$
#40
0"
#42
0$
#47
1!
0'
1&
0%
1$
#50
1"
#52
0$
#57
0!
1'
0&
1%
1$
#60
0"
#62
0$
#67
1!
0'
1&
0%
1$
#70
1"
#72
0$
#77
0!
1'
0&
1%
1$
#80
0"
#82
0$
#87
1!
0'
1&
0%
1$
#90
1"
#92
0$
#97
0!
1'
0&
1%
1$
#100
0"
#102
0$
#107
1!
0'
1&
0%
1$
#110
1"
#112
0$
#117
0!
1'
0&
1%
1$
#120
0"
#122
0$
#127
1!
0'
1&
0%
1$
#130
1"
#132
0$
#137
0!
1'
0&
1%
1$
#140
0"
#142
0$
#147
1!
0'
1&
0%
1$
#150
1"
#152
0$
#157
0!
1'
0&
1%
1$
#160
0"
#162
0$
#167
1!
0'
1&
0%
1$
#170
1"
#172
0$
#177
0!
1'
0&
1%
1$
#180
0"
#182
0$
#187
1!
0'
1&
0%
1$
#190
1"
#192
0$
#197
0!
1'
0&
1%
1$
#200
0"
#202
0$
#207
1!
0'
1&
0%
1$
#210
1"
#212
0$
#217
0!
1'
0&
1%
1$
#220
0"
#222
0$
#227
1!
0'
1&
0%
1$
#230
1"
#232
0$
#237
0!
1'
0&
1%
1$
#240
0"
#242
0$
#247
1!
0'
1&
0%
1$
#250
1"
#252
0$
#257
0!
1'
0&
1%
1$
#260
0"
#262
0$
#267
1!
0'
1&
0%
1$
#270
1"
#272
0$
#277
0!
1'
0&
1%
1$
#280
0"
#282
0$
#287
1!
0'
1&
0%
1$
#290
1"
#292
0$
#297
0!
1'
0&
1%
1$
#300
0"
#302
0$
#307
1!
0'
1&
0%
1$
#310
1"
#312
0$
#317
0!
1'
0&
1%
1$
#320
0"
#322
0$
#327
1!
0'
1&
0%
1$
#330
1"
#332
0$
#337
0!
1'
0&
1%
1$
#340
0"
#342
0$
#347
1!
0'
1&
0%
1$
#350
1"
#352
0$
#357
0!
1'
0&
1%
1$
#360
0"
#362
0$
#367
1!
0'
1&
0%
1$
#370
1"
#372
0$
#377
0!
1'
0&
1%
1$
#380
0"
#382
0$
#387
1!
0'
1&
0%
1$
#390
1"
#392
0$
#397
0!
1'
0&
1%
1$
#400
0"
#402
0$
#407
1!
0'
1&
0%
1$
#410
1"
#412
0$
#417
0!
1'
0&
1%
1$
#420
0"
#422
0$
#427
1!
0'
1&
0%
1$
#430
1"
#432
0$
#437
0!
1'
0&
1%
1$
#440
0"
#442
0$
#447
1!
0'
1&
0%
1$
#450
1"
#452
0$
#457
0!
1'
0&
1%
1$
#460
0"
#462
0$
#467
1!
0'
1&
0%
1$
#470
1"
#472
0$
#477
0!
1'
0&
1%
1$
#480
0"
#482
0$
#487
1!
0'
1&
0%
1$
#490
1"
#492
0$
#497
0!
1'
0&
1%
1$
#500
0"
#502
0$
#507
1!
0'
1&
0%
1$
#510
1"
#512
0$
#517
0!
1'
0&
1%
1$
#520
0"
#522
0$
#527
1!
0'
1&
0%
1$
#530
1"
#532
0$
#537
0!
1'
0&
1%
1$
#540
0"
#542
0$
#547
1!
0'
1&
0%
1$
#550
1"
#552
0$
#557
0!
1'
0&
1%
1$
#560
0"
#562
0$
#567
1!
0'
1&
0%
1$
#570
1"
#572
0$
#577
0!
1'
0&
1%
1$
#580
0"
#582
0$
#587
1!
0'
1&
0%
1$
#590
1"
#592
0$
#597
0!
1'
0&
1%
1$
#600
0"
#602
0$
#607
1!
0'
1&
0%
1$
#610
1"
#612
0$
#617
0!
1'
0&
1%
1$
#620
0"
#622
0$
#627
1!
0'
1&
0%
1$
#630
1"
#632
0$
#637
0!
1'
0&
1%
1$
#640
0"
#642
0$
#647
1!
0'
1&
0%
1$
#650
1"
#652
0$
#657
0!
1'
0&
1%
1$
#660
0"
#662
0$
#667
1!
0'
1&
0%
1$
#670
1"
#672
0$
#677
0!
1'
0&
1%
1$
#680
0"
#682
0$
#687
1!
0'
1&
0%
1$
#690
1"
#692
0$
#697
0!
1'
0&
1%
1$
#700
0"
#702
0$
#707
1!
0'
1&
0%
1$
#710
1"
#712
0$
#717
0!
1'
0&
1%
1$
#720
0"
#722
0$
#727
1!
0'
1&
0%
1$
#730
1"
#732
0$
#737
0!
1'
0&
1%
1$
#740
0"
#742
0$
#747
1!
0'
1&
0%
1$
#750
1"
#752
0$
#757
0!
1'
0&
1%
1$
#760
0"
#762
0$
#767
1!
0'
1&
0%
1$
#770
1"
#772
0$
#777
0!
1'
0&
1%
1$
#780
0"
#782
0$
#787
1!
0'
1&
0%
1$
#790
1"
#792
0$
#797
0!
1'
0&
1%
1$
#800
0"
#802
0$
#807
1!
0'
1&
0%
1$
#810
1"
#812
0$
#817
0!
1'
0&
1%
1$
#820
0"
#822
0$
#827
1!
0'
1&
0%
1$
#830
1"
#832
0$
#837
0!
1'
0&
1%
1$
#840
0"
#842
0$
#847
1!
0'
1&
0%
1$
#850
1"
#852
0$
#857
0!
1'
0&
1%
1$
#860
0"
#862
0$
#867
1!
0'
1&
0%
1$
#870
1"
#872
0$
#877
0!
1'
0&
1%
1$
#880
0"
#882
0$
#887
1!
0'
1&
0%
1$
#890
1"
#892
0$
#897
0!
1'
0&
1%
1$
#900
0"
#902
0$
#907
1!
0'
1&
0%
1$
#910
1"
#912
0$
#917
0!
1'
0&
1%
1$
#920
0"
#922
0$
#927
1!
0'
1&
0%
1$
#930
1"
#932
0$
#937
0!
1'
0&
1%
1$
#940
0"
#942
0$
#947
1!
0'
1&
0%
1$
#950
1"
#952
0$
#957
0!
1'
0&
1%
1$
#960
0"
#962
0$
#967
1!
0'
1&
0%
1$
#970
1"
#972
0$
#977
0!
1'
0&
1%
1$
#980
0"
#982
0$
#987
1!
0'
1&
0%
1$
#990
1"
#992
0$
#997
0!
1'
0&
1%
1$
#1000
0"
