FSM/serialAdder/serialAdder.v
//behavioural description of Serial Adder
/*
module serialAdder(S,Cout,A,B,clk,reset);
	input A,B,clk,reset;
	output reg S,Cout;

	always @ (posedge clk , posedge reset) begin
		if (reset) begin
			Cout <= 0;
			S <= 0;
		end
		else {Cout,S} <= A+B+Cout;
	end
endmodule
*/

//mealy state diagram for a serial serialAdder
module serialAdder(S,Cout,A,B,clk,reset);
	input A,B,clk,reset;
	output reg S,Cout;

	always @ (posedge clk , posedge reset) begin
	if (reset) begin
		Cout <= 0;
		S <= 0;
	end
	else
		case (Cout)
			0 : case ({A,B})
						2'b00 : begin Cout <= 0; S <= 0; end
						2'b01 : begin Cout <= 0; S <= 1; end
						2'b10 : begin Cout <= 0; S <= 1; end
						2'b11 : begin Cout <= 1; S <= 0; end
						default : begin Cout <= 0; S <= 0; end
					endcase
			1 : case ({A,B})
			 			2'b00 : begin Cout <= 0; S <= 1; end
						2'b01 : begin Cout <= 1; S <= 0; end
						2'b10 : begin Cout <= 1; S <= 0; end
						2'b11 : begin Cout <= 1; S <= 1; end
						default : begin Cout <= 0; S <= 0; end
					endcase
			default : begin Cout <= 0; S <= 0; end
		endcase
	end
endmodule

module testbench;
	reg A,B,clk,reset;
	wire S,Cout;
	reg [7:0] inputA = 8'b00100110;
	reg [7:0] inputB = 8'b10111011;
	integer i;
	serialAdder DUT (S,Cout,A,B,clk,reset);

 	always #5 clk = ~clk;

	initial begin
		$dumpfile ("waveform.vcd");
		$dumpvars (0,testbench);
		clk=0;
		reset=0;
		#1 reset=1;
		#1 reset=0;
		$display("InputA=%b",inputA);
		$display("InputB=%b",inputB);
		$display("------------------------");
		for (i=0;i<8;i=i+1) begin
			A = inputA[i];
			B = inputB[i];
			#10 $display ("time = %2d : i= %1d : A=%b : B=%b : S=%b : Cout=%b",$time,i,A,B,S,Cout);
		end
	end
	initial #100 $finish;
endmodule

FSM/serialAdder/waveform.vcd
$date
	Wed Sep 23 20:59:47 2020
$end
$version
	Icarus Verilog
$end
$timescale
	1s
$end
$scope module testbench $end
$var wire 1 ! S $end
$var wire 1 " Cout $end
$var reg 1 # A $end
$var reg 1 $ B $end
$var reg 1 % clk $end
$var reg 8 & inputA [7:0] $end
$var reg 8 ' inputB [7:0] $end
$var reg 1 ( reset $end
$var integer 32 ) i [31:0] $end
$scope module DUT $end
$var wire 1 # A $end
$var wire 1 $ B $end
$var wire 1 % clk $end
$var wire 1 ( reset $end
$var reg 1 " Cout $end
$var reg 1 ! S $end
$upscope $end
$upscope $end
$enddefinitions $end
#0
$dumpvars
bx )
0(
b10111011 '
b100110 &
0%
x$
x#
x"
x!
$end
#1
0!
0"
1(
#2
1$
0#
b0 )
0(
#5
1!
1%
#10
0%
#12
1#
b1 )
#15
0!
1"
1%
#20
0%
#22
0$
b10 )
#25
1%
#30
0%
#32
1$
0#
b11 )
#35
1%
#40
0%
#42
b100 )
#45
1%
#50
0%
#52
1#
b101 )
#55
1!
1%
#60
0%
#62
0$
0#
b110 )
#65
0"
1%
#70
0%
#72
1$
b111 )
#75
1%
#80
0%
#82
b1000 )
