SRlatch/SRlatch.v
module SRlatch (Q,Qbar,S,R);
  input S,R;
  output Q,Qbar;

  assign Q = ~(R&Qbar);
  assign Qbar = ~(S&Q);
endmodule

module testbench;
  reg S,R;
  wire Q,Qbar;
  SRlatch DUT(Q,Qbar,S,R);
  initial begin
    $dumpfile("SRlatch.vcd");
    $dumpvars(0,testbench);
    $monitor($time," S=%b,R=%b,Q=%b,Q'=%b",S,R,Q,Qbar);
    #1 S = 1'b0; R = 1'b0;
    #1 S = 1'b0; R = 1'b1;
    #1 S = 1'b1; R = 1'b0;
    #1 S = 1'b1; R = 1'b1;
    #1 S = 1'b0; R = 1'b1;
    #1 S = 1'b1; R = 1'b1;
    #1 S = 1'b0; R = 1'b0;
    #1 S = 1'b1; R = 1'b1;  //here the simulator Hangs up
    #1 $finish;
  end
endmodule

SRlatch/SRlatch.vcd
$date
	Sat Aug 29 17:27:46 2020
$end
$version
	Icarus Verilog
$end
$timescale
	1s
$end
$scope module testbench $end
$var wire 1 ! Qbar $end
$var wire 1 " Q $end
$var reg 1 # R $end
$var reg 1 $ S $end
$scope module DUT $end
$var wire 1 " Q $end
$var wire 1 ! Qbar $end
$var wire 1 # R $end
$var wire 1 $ S $end
$upscope $end
$upscope $end
$enddefinitions $end
#0
$dumpvars
x$
x#
x"
x!
$end
#1
1"
1!
0#
0$
#2
0"
1#
#3
0!
1"
0#
1$
#4
1#
#5
0"
1!
0$
#6
1$
#7
1"
0#
0$
